LICENSE
MANIFEST.in
README.md
setup.py
pygrape/__init__.py
pygrape/pygrape.py
pygrape/pygrape_example.py
pygrape.egg-info/PKG-INFO
pygrape.egg-info/SOURCES.txt
pygrape.egg-info/dependency_links.txt
pygrape.egg-info/top_level.txt