Metadata-Version: 1.0
Name: pygrape
Version: 1.1
Summary: pygrape is a python library for updating terminal output in realtime
Home-page: https://github.com/Leviathan1995/pygrape
Author: leviathan1995
Author-email: leviathan0992@gmail.com
License: MIT
Platform: UNKNOWN
